BaseDeploy/BaseDeploy.py
BaseDeploy/__init__.py
BaseDeploy/version.py
BaseDeploy-0.0.4.dist-info/METADATA
BaseDeploy-0.0.4.dist-info/WHEEL
BaseDeploy-0.0.4.dist-info/entry_points.txt
BaseDeploy-0.0.4.dist-info/top_level.txt
BaseDeploy-0.0.4.dist-info/zip-safe
BaseDeploy-0.0.4.dist-info/RECORD
