Metadata-Version: 2.1
Name: BaseDeploy
Version: 0.0.4
Summary: BaseDeploy is a simple deployment tool made by XEdu.
Home-page: https://github.com/OpenXLab-Edu/OpenMMLab-Edu
Author: OpenXLab
Author-email: wangbolun@pjlab.org.cn
License: MIT License
Platform: UNKNOWN
Requires-Python: >=3.6
Requires-Dist: opencv-python (>=4.1.2.30)
Requires-Dist: BaseDT
Requires-Dist: numpy
Requires-Dist: matplotlib
Requires-Dist: onnxruntime
